ragger/__init__.py
ragger/__version__.py
ragger/error.py
ragger/logger.py
ragger/py.typed
ragger/backend/__init__.py
ragger/backend/interface.py
ragger/backend/ledgercomm.py
ragger/backend/ledgerwallet.py
ragger/backend/physical_backend.py
ragger/backend/speculos.py
ragger/backend/stub.py
ragger/bip/__init__.py
ragger/bip/path.py
ragger/bip/seed.py
ragger/conftest/__init__.py
ragger/conftest/base_conftest.py
ragger/conftest/configuration.py
ragger/firmware/__init__.py
ragger/firmware/structs.py
ragger/firmware/touch/__init__.py
ragger/firmware/touch/element.py
ragger/firmware/touch/layouts.py
ragger/firmware/touch/positions.py
ragger/firmware/touch/screen.py
ragger/firmware/touch/use_cases.py
ragger/gui/__init__.py
ragger/gui/interface.py
ragger/gui/process.py
ragger/gui/assets/nanos_body.png
ragger/gui/assets/nanos_leftbutton.png
ragger/gui/assets/nanos_rightbutton.png
ragger/gui/assets/nanosp_body.png
ragger/gui/assets/nanosp_leftbutton.png
ragger/gui/assets/nanosp_rightbutton.png
ragger/gui/assets/nanox_body.png
ragger/gui/assets/nanox_leftbutton.png
ragger/gui/assets/nanox_rightbutton.png
ragger/gui/assets/stax_body.png
ragger/gui/assets/swipe_left_action.png
ragger/gui/assets/swipe_right_action.png
ragger/gui/assets/touch_action.png
ragger/navigator/__init__.py
ragger/navigator/instruction.py
ragger/navigator/nano_navigator.py
ragger/navigator/navigation_scenario.py
ragger/navigator/navigator.py
ragger/navigator/touch_navigator.py
ragger/utils/__init__.py
ragger/utils/misc.py
ragger/utils/packing.py
ragger/utils/structs.py
ragger-1.42.0.dist-info/licenses/LICENSE
ragger-1.42.0.dist-info/METADATA
ragger-1.42.0.dist-info/WHEEL
ragger-1.42.0.dist-info/top_level.txt
ragger-1.42.0.dist-info/RECORD
