Metadata-Version: 2.4
Name: ragger
Version: 1.42.0
Summary: Testing framework using Speculos and LedgerComm as backends
Author-email: Ledger <hello@ledger.fr>
Project-URL: Homepage, https://github.com/LedgerHQ/ragger
Project-URL: Bug Tracker, https://github.com/LedgerHQ/ragger/issues
Classifier: Programming Language :: Python :: 3
Classifier: Programming Language :: Python :: 3.9
Classifier: Programming Language :: Python :: 3.10
Classifier: Programming Language :: Python :: 3.11
Classifier: Programming Language :: Python :: 3.12
Classifier: Programming Language :: Python :: 3.13
Classifier: License :: OSI Approved :: Apache Software License
Classifier: Operating System :: POSIX :: Linux
Classifier: Operating System :: MacOS :: MacOS X
Requires-Python: >=3.9
License-File: LICENSE
Requires-Dist: bip_utils>=2.4.0
Requires-Dist: py-sr25519-bindings<0.3.0,>=0.2.0
Requires-Dist: ledgered>=0.10.1
Requires-Dist: toml
Provides-Extra: tests
Requires-Dist: pytest; extra == "tests"
Requires-Dist: pytest-cov; extra == "tests"
Provides-Extra: checkers
Requires-Dist: yapf; extra == "checkers"
Requires-Dist: toml; extra == "checkers"
Requires-Dist: flake8; extra == "checkers"
Requires-Dist: flake8-pyproject; extra == "checkers"
Requires-Dist: mypy; extra == "checkers"
Requires-Dist: types-toml; extra == "checkers"
Requires-Dist: bandit; extra == "checkers"
Provides-Extra: doc
Requires-Dist: pylint; extra == "doc"
Requires-Dist: sphinx; extra == "doc"
Requires-Dist: sphinx-rtd-theme; extra == "doc"
Requires-Dist: sphinxcontrib-images; extra == "doc"
Requires-Dist: sphinx-copybutton; extra == "doc"
Requires-Dist: Jinja2>=3.0; extra == "doc"
Requires-Dist: docutils==0.16; extra == "doc"
Provides-Extra: speculos
Requires-Dist: speculos>=0.13.1; extra == "speculos"
Requires-Dist: mnemonic; extra == "speculos"
Provides-Extra: ledgercomm
Requires-Dist: ledgercomm>=1.2.1; extra == "ledgercomm"
Requires-Dist: ledgercomm[hid]>=1.2.1; extra == "ledgercomm"
Requires-Dist: pyqt6; extra == "ledgercomm"
Requires-Dist: pytesseract; extra == "ledgercomm"
Requires-Dist: pillow; extra == "ledgercomm"
Provides-Extra: ledgerwallet
Requires-Dist: ledgerwallet>=0.4.0; extra == "ledgerwallet"
Requires-Dist: pyqt6; extra == "ledgerwallet"
Requires-Dist: pytesseract; extra == "ledgerwallet"
Requires-Dist: pillow; extra == "ledgerwallet"
Provides-Extra: all-backends
Requires-Dist: ragger[speculos]; extra == "all-backends"
Requires-Dist: ragger[ledgercomm]; extra == "all-backends"
Requires-Dist: ragger[ledgerwallet]; extra == "all-backends"
Dynamic: license-file
